invoicing/__init__.py
invoicing/invoice.py
jed_invoicepdf-0.1.0.post3.dist-info/METADATA
jed_invoicepdf-0.1.0.post3.dist-info/WHEEL
jed_invoicepdf-0.1.0.post3.dist-info/top_level.txt
jed_invoicepdf-0.1.0.post3.dist-info/RECORD
